[
  {
    "date": "2025-05-25",
    "leetcode_ids": [
      "two-sum",
      "Remove-Duplicates-from-Sorted-List",
      "Remove-Duplicates-from-Sorted-List-II"
    ],
    "description": "Day 1 of #100DaysOfLeetCode<br>Pattern: Two Pointer Pattern<br>Solved Problems",
    "tags": [
      "DSA",
      "100daysOfDSA",
      "Leetcode"
    ],
    "images": [
      "Screenshot 2025-05-25 100450.png",
      "Screenshot 2025-05-25 101723.png",
      "Screenshot 2025-05-25 103336.png"
    ]
  },
  {
    "date": "2025-05-26",
    "leetcode_ids": [
      "find-the-duplicate-number",
      "duplicate-zeros",
      "remove-duplicates-from-sorted-array-ii"
    ],
    "description": "Day 2 of #100DaysOfLeetCode<br>Pattern: Two Pointer Pattern<br>Solved Problems",
    "tags": [
      "#DSA",
      "#100daysOfDSA",
      "#leetcode",
      "DSA",
      "100daysOfDSA",
      "Leetcode"
    ],
    "images": [
      "20250526_213020_Screenshot 2025-05-26 094529.png",
      "20250526_213020_Screenshot 2025-05-26 100627.png",
      "20250526_213020_Screenshot 2025-05-26 212444.png"
    ]
  }
]
